LICENSE
setup.py
pikacloudlib/PIL_extend.py
pikacloudlib/__init__.py
pikacloudlib/all.py
pikacloudlib/c.py
pikacloudlib/code.py
pikacloudlib/color.py
pikacloudlib/data.py
pikacloudlib/dsfAdmin.py
pikacloudlib/err.py
pikacloudlib/help.py
pikacloudlib/http_spider.py
pikacloudlib/image.py
pikacloudlib/log_in.py
pikacloudlib/mail.py
pikacloudlib/print.py
pikacloudlib/print_format.py
pikacloudlib/print_logo.py
pikacloudlib/pygame_extend.py
pikacloudlib/python_plot.py
pikacloudlib/render.py
pikacloudlib/spark_word.py
pikacloudlib/spell.py
pikacloudlib/tkinter_extend.py
pikacloudlib/updata_yourpackage.py
pikacloudlib/user.py
pikacloudlib/venv_install.py
pikacloudlib/xesapi.py
pikacloudlib/xesapp.py
pikacloudlib/xesuser.py
pikacloudlib.egg-info/PKG-INFO
pikacloudlib.egg-info/SOURCES.txt
pikacloudlib.egg-info/dependency_links.txt
pikacloudlib.egg-info/top_level.txt
pikacloudlib/numpy/__init__.py
pikacloudlib/numpy/f.py
pikacloudlib/request/__init__.py
pikacloudlib/request/get_news.py
pikacloudlib/request/internal_module.py
pikacloudlib/request/xes.py