Metadata-Version: 2.1
Name: pikacloudlib
Version: 1.0.0
Summary: Pika~Studio学而思专用库
Home-page: https://github.com/
Author: Junwei Xiong
Author-email: xiongmc136@qq.com
License: UNKNOWN
Platform: UNKNOWN
Classifier: Programming Language :: Python :: 3
Classifier: License :: OSI Approved :: MIT License
Classifier: Operating System :: OS Independent
License-File: LICENSE
